{
	"name": "DashBar",
	"plugin-id": "Sprite",
	"sid": 952175668214950,
	"isGlobal": false,
	"instanceVariables": [],
	"behaviorTypes": [
		{
			"behaviorId": "Pin",
			"name": "Pin",
			"sid": 600181611116883
		}
	],
	"effectTypes": [],
	"animations": {
		"items": [
			{
				"frames": [
					{
						"width": 41,
						"height": 8,
						"originX": 0.5121951219512195,
						"originY": 0.5,
						"originalSource": "",
						"exportFormat": "png",
						"exportQuality": 0.8,
						"imageSpriteId": 912550,
						"useCollisionPoly": true,
						"duration": 1
					},
					{
						"width": 41,
						"height": 8,
						"originX": 0.5121951219512195,
						"originY": 0.5,
						"originalSource": "",
						"exportFormat": "png",
						"exportQuality": 0.8,
						"imageSpriteId": 2296081,
						"useCollisionPoly": true,
						"duration": 1
					},
					{
						"width": 41,
						"height": 8,
						"originX": 0.5121951219512195,
						"originY": 0.5,
						"originalSource": "",
						"exportFormat": "png",
						"exportQuality": 0.8,
						"imageSpriteId": 8311014,
						"useCollisionPoly": true,
						"duration": 1
					},
					{
						"width": 41,
						"height": 8,
						"originX": 0.5121951219512195,
						"originY": 0.5,
						"originalSource": "",
						"exportFormat": "png",
						"exportQuality": 0.8,
						"imageSpriteId": 4225159,
						"useCollisionPoly": true,
						"duration": 1
					},
					{
						"width": 41,
						"height": 8,
						"originX": 0.5121951219512195,
						"originY": 0.5,
						"originalSource": "",
						"exportFormat": "png",
						"exportQuality": 0.8,
						"imageSpriteId": 9160003,
						"useCollisionPoly": true,
						"duration": 1
					},
					{
						"width": 41,
						"height": 8,
						"originX": 0.5121951219512195,
						"originY": 0.5,
						"originalSource": "",
						"exportFormat": "png",
						"exportQuality": 0.8,
						"imageSpriteId": 526669,
						"useCollisionPoly": true,
						"duration": 1
					},
					{
						"width": 41,
						"height": 8,
						"originX": 0.5121951219512195,
						"originY": 0.5,
						"originalSource": "",
						"exportFormat": "png",
						"exportQuality": 0.8,
						"imageSpriteId": 8459542,
						"useCollisionPoly": true,
						"duration": 1
					},
					{
						"width": 41,
						"height": 8,
						"originX": 0.5121951219512195,
						"originY": 0.5,
						"originalSource": "",
						"exportFormat": "png",
						"exportQuality": 0.8,
						"imageSpriteId": 8780809,
						"useCollisionPoly": true,
						"duration": 1
					},
					{
						"width": 41,
						"height": 8,
						"originX": 0.5121951219512195,
						"originY": 0.5,
						"originalSource": "",
						"exportFormat": "png",
						"exportQuality": 0.8,
						"imageSpriteId": 5203849,
						"useCollisionPoly": true,
						"duration": 1
					},
					{
						"width": 41,
						"height": 8,
						"originX": 0.5121951219512195,
						"originY": 0.5,
						"originalSource": "",
						"exportFormat": "png",
						"exportQuality": 0.8,
						"imageSpriteId": 1913561,
						"useCollisionPoly": true,
						"duration": 1
					},
					{
						"width": 41,
						"height": 8,
						"originX": 0.5121951219512195,
						"originY": 0.5,
						"originalSource": "",
						"exportFormat": "png",
						"exportQuality": 0.8,
						"imageSpriteId": 3796489,
						"useCollisionPoly": true,
						"duration": 1
					},
					{
						"width": 41,
						"height": 8,
						"originX": 0.5121951219512195,
						"originY": 0.5,
						"originalSource": "",
						"exportFormat": "png",
						"exportQuality": 0.8,
						"imageSpriteId": 3563913,
						"useCollisionPoly": true,
						"duration": 1
					},
					{
						"width": 41,
						"height": 8,
						"originX": 0.5121951219512195,
						"originY": 0.5,
						"originalSource": "",
						"exportFormat": "png",
						"exportQuality": 0.8,
						"imageSpriteId": 1502543,
						"useCollisionPoly": true,
						"duration": 1
					},
					{
						"width": 41,
						"height": 8,
						"originX": 0.5121951219512195,
						"originY": 0.5,
						"originalSource": "",
						"exportFormat": "png",
						"exportQuality": 0.8,
						"imageSpriteId": 5181661,
						"useCollisionPoly": true,
						"duration": 1
					},
					{
						"width": 41,
						"height": 8,
						"originX": 0.5121951219512195,
						"originY": 0.5,
						"originalSource": "",
						"exportFormat": "png",
						"exportQuality": 0.8,
						"imageSpriteId": 8275410,
						"useCollisionPoly": true,
						"duration": 1
					},
					{
						"width": 41,
						"height": 8,
						"originX": 0.5121951219512195,
						"originY": 0.5,
						"originalSource": "",
						"exportFormat": "png",
						"exportQuality": 0.8,
						"imageSpriteId": 4186426,
						"useCollisionPoly": true,
						"duration": 1
					},
					{
						"width": 41,
						"height": 8,
						"originX": 0.5121951219512195,
						"originY": 0.5,
						"originalSource": "",
						"exportFormat": "png",
						"exportQuality": 0.8,
						"imageSpriteId": 4384721,
						"useCollisionPoly": true,
						"duration": 1
					},
					{
						"width": 41,
						"height": 8,
						"originX": 0.5121951219512195,
						"originY": 0.5,
						"originalSource": "",
						"exportFormat": "png",
						"exportQuality": 0.8,
						"imageSpriteId": 1502142,
						"useCollisionPoly": true,
						"duration": 1
					},
					{
						"width": 41,
						"height": 8,
						"originX": 0.5121951219512195,
						"originY": 0.5,
						"originalSource": "",
						"exportFormat": "png",
						"exportQuality": 0.8,
						"imageSpriteId": 3859373,
						"useCollisionPoly": true,
						"duration": 1
					},
					{
						"width": 41,
						"height": 8,
						"originX": 0.5121951219512195,
						"originY": 0.5,
						"originalSource": "",
						"exportFormat": "png",
						"exportQuality": 0.8,
						"imageSpriteId": 4781467,
						"useCollisionPoly": true,
						"duration": 1
					},
					{
						"width": 41,
						"height": 8,
						"originX": 0.5121951219512195,
						"originY": 0.5,
						"originalSource": "",
						"exportFormat": "png",
						"exportQuality": 0.8,
						"imageSpriteId": 6508497,
						"useCollisionPoly": true,
						"duration": 1
					},
					{
						"width": 41,
						"height": 8,
						"originX": 0.5121951219512195,
						"originY": 0.5,
						"originalSource": "",
						"exportFormat": "png",
						"exportQuality": 0.8,
						"imageSpriteId": 668862,
						"useCollisionPoly": true,
						"duration": 1
					},
					{
						"width": 41,
						"height": 8,
						"originX": 0.5121951219512195,
						"originY": 0.5,
						"originalSource": "",
						"exportFormat": "png",
						"exportQuality": 0.8,
						"imageSpriteId": 8996011,
						"useCollisionPoly": true,
						"duration": 1
					},
					{
						"width": 41,
						"height": 8,
						"originX": 0.5121951219512195,
						"originY": 0.5,
						"originalSource": "",
						"exportFormat": "png",
						"exportQuality": 0.8,
						"imageSpriteId": 1361777,
						"useCollisionPoly": true,
						"duration": 1
					},
					{
						"width": 41,
						"height": 8,
						"originX": 0.5121951219512195,
						"originY": 0.5,
						"originalSource": "",
						"exportFormat": "png",
						"exportQuality": 0.8,
						"imageSpriteId": 5903408,
						"useCollisionPoly": true,
						"duration": 1
					},
					{
						"width": 41,
						"height": 8,
						"originX": 0.5121951219512195,
						"originY": 0.5,
						"originalSource": "",
						"exportFormat": "png",
						"exportQuality": 0.8,
						"imageSpriteId": 5054577,
						"useCollisionPoly": true,
						"duration": 1
					},
					{
						"width": 41,
						"height": 8,
						"originX": 0.5121951219512195,
						"originY": 0.5,
						"originalSource": "",
						"exportFormat": "png",
						"exportQuality": 0.8,
						"imageSpriteId": 6108000,
						"useCollisionPoly": true,
						"duration": 1
					},
					{
						"width": 41,
						"height": 8,
						"originX": 0.5121951219512195,
						"originY": 0.5,
						"originalSource": "",
						"exportFormat": "png",
						"exportQuality": 0.8,
						"imageSpriteId": 6098145,
						"useCollisionPoly": true,
						"duration": 1
					},
					{
						"width": 41,
						"height": 8,
						"originX": 0.5121951219512195,
						"originY": 0.5,
						"originalSource": "",
						"exportFormat": "png",
						"exportQuality": 0.8,
						"imageSpriteId": 5658279,
						"useCollisionPoly": true,
						"duration": 1
					},
					{
						"width": 41,
						"height": 8,
						"originX": 0.5121951219512195,
						"originY": 0.5,
						"originalSource": "",
						"exportFormat": "png",
						"exportQuality": 0.8,
						"imageSpriteId": 5449926,
						"useCollisionPoly": true,
						"duration": 1
					},
					{
						"width": 41,
						"height": 8,
						"originX": 0.5121951219512195,
						"originY": 0.5,
						"originalSource": "",
						"exportFormat": "png",
						"exportQuality": 0.8,
						"imageSpriteId": 4867653,
						"useCollisionPoly": true,
						"duration": 1
					},
					{
						"width": 41,
						"height": 8,
						"originX": 0.5121951219512195,
						"originY": 0.5,
						"originalSource": "",
						"exportFormat": "png",
						"exportQuality": 0.8,
						"imageSpriteId": 1710476,
						"useCollisionPoly": true,
						"duration": 1
					},
					{
						"width": 41,
						"height": 8,
						"originX": 0.5121951219512195,
						"originY": 0.5,
						"originalSource": "",
						"exportFormat": "png",
						"exportQuality": 0.8,
						"imageSpriteId": 4974467,
						"useCollisionPoly": true,
						"duration": 1
					},
					{
						"width": 41,
						"height": 8,
						"originX": 0.5121951219512195,
						"originY": 0.5,
						"originalSource": "",
						"exportFormat": "png",
						"exportQuality": 0.8,
						"imageSpriteId": 1676467,
						"useCollisionPoly": true,
						"duration": 1
					},
					{
						"width": 41,
						"height": 8,
						"originX": 0.5121951219512195,
						"originY": 0.5,
						"originalSource": "",
						"exportFormat": "png",
						"exportQuality": 0.8,
						"imageSpriteId": 1680890,
						"useCollisionPoly": true,
						"duration": 1
					},
					{
						"width": 41,
						"height": 8,
						"originX": 0.5121951219512195,
						"originY": 0.5,
						"originalSource": "",
						"exportFormat": "png",
						"exportQuality": 0.8,
						"imageSpriteId": 433330,
						"useCollisionPoly": true,
						"duration": 1
					},
					{
						"width": 41,
						"height": 8,
						"originX": 0.5121951219512195,
						"originY": 0.5,
						"originalSource": "",
						"exportFormat": "png",
						"exportQuality": 0.8,
						"imageSpriteId": 1845312,
						"useCollisionPoly": true,
						"duration": 1
					},
					{
						"width": 41,
						"height": 8,
						"originX": 0.5121951219512195,
						"originY": 0.5,
						"originalSource": "",
						"exportFormat": "png",
						"exportQuality": 0.8,
						"imageSpriteId": 1532180,
						"useCollisionPoly": true,
						"duration": 1
					},
					{
						"width": 41,
						"height": 8,
						"originX": 0.5121951219512195,
						"originY": 0.5,
						"originalSource": "",
						"exportFormat": "png",
						"exportQuality": 0.8,
						"imageSpriteId": 6728291,
						"useCollisionPoly": true,
						"duration": 1
					},
					{
						"width": 41,
						"height": 8,
						"originX": 0.5121951219512195,
						"originY": 0.5,
						"originalSource": "",
						"exportFormat": "png",
						"exportQuality": 0.8,
						"imageSpriteId": 2545240,
						"useCollisionPoly": true,
						"duration": 1
					}
				],
				"sid": 470518479254369,
				"name": "Normal",
				"isLooping": false,
				"isPingPong": false,
				"repeatCount": 1,
				"repeatTo": 0,
				"speed": 25
			},
			{
				"frames": [
					{
						"width": 41,
						"height": 8,
						"originX": 0.5121951219512195,
						"originY": 0.5,
						"originalSource": "",
						"exportFormat": "png",
						"exportQuality": 0.8,
						"imageSpriteId": 6794065,
						"useCollisionPoly": true,
						"duration": 1
					},
					{
						"width": 41,
						"height": 8,
						"originX": 0.5121951219512195,
						"originY": 0.5,
						"originalSource": "",
						"exportFormat": "png",
						"exportQuality": 0.8,
						"imageSpriteId": 2324016,
						"useCollisionPoly": true,
						"duration": 1
					},
					{
						"width": 41,
						"height": 8,
						"originX": 0.5121951219512195,
						"originY": 0.5,
						"originalSource": "",
						"exportFormat": "png",
						"exportQuality": 0.8,
						"imageSpriteId": 4227632,
						"useCollisionPoly": true,
						"duration": 1
					},
					{
						"width": 41,
						"height": 8,
						"originX": 0.5121951219512195,
						"originY": 0.5,
						"originalSource": "",
						"exportFormat": "png",
						"exportQuality": 0.8,
						"imageSpriteId": 1128698,
						"useCollisionPoly": true,
						"duration": 1
					},
					{
						"width": 41,
						"height": 8,
						"originX": 0.5121951219512195,
						"originY": 0.5,
						"originalSource": "",
						"exportFormat": "png",
						"exportQuality": 0.8,
						"imageSpriteId": 5653916,
						"useCollisionPoly": true,
						"duration": 1
					},
					{
						"width": 41,
						"height": 8,
						"originX": 0.5121951219512195,
						"originY": 0.5,
						"originalSource": "",
						"exportFormat": "png",
						"exportQuality": 0.8,
						"imageSpriteId": 3067983,
						"useCollisionPoly": true,
						"duration": 1
					},
					{
						"width": 41,
						"height": 8,
						"originX": 0.5121951219512195,
						"originY": 0.5,
						"originalSource": "",
						"exportFormat": "png",
						"exportQuality": 0.8,
						"imageSpriteId": 71639,
						"useCollisionPoly": true,
						"duration": 1
					},
					{
						"width": 41,
						"height": 8,
						"originX": 0.5121951219512195,
						"originY": 0.5,
						"originalSource": "",
						"exportFormat": "png",
						"exportQuality": 0.8,
						"imageSpriteId": 8450829,
						"useCollisionPoly": true,
						"duration": 1
					},
					{
						"width": 41,
						"height": 8,
						"originX": 0.5121951219512195,
						"originY": 0.5,
						"originalSource": "",
						"exportFormat": "png",
						"exportQuality": 0.8,
						"imageSpriteId": 6255746,
						"useCollisionPoly": true,
						"duration": 1
					},
					{
						"width": 41,
						"height": 8,
						"originX": 0.5121951219512195,
						"originY": 0.5,
						"originalSource": "",
						"exportFormat": "png",
						"exportQuality": 0.8,
						"imageSpriteId": 5018119,
						"useCollisionPoly": true,
						"duration": 1
					},
					{
						"width": 41,
						"height": 8,
						"originX": 0.5121951219512195,
						"originY": 0.5,
						"originalSource": "",
						"exportFormat": "png",
						"exportQuality": 0.8,
						"imageSpriteId": 3353158,
						"useCollisionPoly": true,
						"duration": 1
					},
					{
						"width": 41,
						"height": 8,
						"originX": 0.5121951219512195,
						"originY": 0.5,
						"originalSource": "",
						"exportFormat": "png",
						"exportQuality": 0.8,
						"imageSpriteId": 1775053,
						"useCollisionPoly": true,
						"duration": 1
					},
					{
						"width": 41,
						"height": 8,
						"originX": 0.5121951219512195,
						"originY": 0.5,
						"originalSource": "",
						"exportFormat": "png",
						"exportQuality": 0.8,
						"imageSpriteId": 6532118,
						"useCollisionPoly": true,
						"duration": 1
					},
					{
						"width": 41,
						"height": 8,
						"originX": 0.5121951219512195,
						"originY": 0.5,
						"originalSource": "",
						"exportFormat": "png",
						"exportQuality": 0.8,
						"imageSpriteId": 898302,
						"useCollisionPoly": true,
						"duration": 1
					},
					{
						"width": 41,
						"height": 8,
						"originX": 0.5121951219512195,
						"originY": 0.5,
						"originalSource": "",
						"exportFormat": "png",
						"exportQuality": 0.8,
						"imageSpriteId": 3204312,
						"useCollisionPoly": true,
						"duration": 1
					},
					{
						"width": 41,
						"height": 8,
						"originX": 0.5121951219512195,
						"originY": 0.5,
						"originalSource": "",
						"exportFormat": "png",
						"exportQuality": 0.8,
						"imageSpriteId": 6617484,
						"useCollisionPoly": true,
						"duration": 1
					},
					{
						"width": 41,
						"height": 8,
						"originX": 0.5121951219512195,
						"originY": 0.5,
						"originalSource": "",
						"exportFormat": "png",
						"exportQuality": 0.8,
						"imageSpriteId": 6297548,
						"useCollisionPoly": true,
						"duration": 1
					},
					{
						"width": 41,
						"height": 8,
						"originX": 0.5121951219512195,
						"originY": 0.5,
						"originalSource": "",
						"exportFormat": "png",
						"exportQuality": 0.8,
						"imageSpriteId": 1015224,
						"useCollisionPoly": true,
						"duration": 1
					},
					{
						"width": 41,
						"height": 8,
						"originX": 0.5121951219512195,
						"originY": 0.5,
						"originalSource": "",
						"exportFormat": "png",
						"exportQuality": 0.8,
						"imageSpriteId": 7724476,
						"useCollisionPoly": true,
						"duration": 1
					},
					{
						"width": 41,
						"height": 8,
						"originX": 0.5121951219512195,
						"originY": 0.5,
						"originalSource": "",
						"exportFormat": "png",
						"exportQuality": 0.8,
						"imageSpriteId": 4347778,
						"useCollisionPoly": true,
						"duration": 1
					},
					{
						"width": 41,
						"height": 8,
						"originX": 0.5121951219512195,
						"originY": 0.5,
						"originalSource": "",
						"exportFormat": "png",
						"exportQuality": 0.8,
						"imageSpriteId": 3492636,
						"useCollisionPoly": true,
						"duration": 1
					},
					{
						"width": 41,
						"height": 8,
						"originX": 0.5121951219512195,
						"originY": 0.5,
						"originalSource": "",
						"exportFormat": "png",
						"exportQuality": 0.8,
						"imageSpriteId": 4477206,
						"useCollisionPoly": true,
						"duration": 1
					},
					{
						"width": 41,
						"height": 8,
						"originX": 0.5121951219512195,
						"originY": 0.5,
						"originalSource": "",
						"exportFormat": "png",
						"exportQuality": 0.8,
						"imageSpriteId": 3475640,
						"useCollisionPoly": true,
						"duration": 1
					},
					{
						"width": 41,
						"height": 8,
						"originX": 0.5121951219512195,
						"originY": 0.5,
						"originalSource": "",
						"exportFormat": "png",
						"exportQuality": 0.8,
						"imageSpriteId": 983426,
						"useCollisionPoly": true,
						"duration": 1
					},
					{
						"width": 41,
						"height": 8,
						"originX": 0.5121951219512195,
						"originY": 0.5,
						"originalSource": "",
						"exportFormat": "png",
						"exportQuality": 0.8,
						"imageSpriteId": 6041683,
						"useCollisionPoly": true,
						"duration": 1
					},
					{
						"width": 41,
						"height": 8,
						"originX": 0.5121951219512195,
						"originY": 0.5,
						"originalSource": "",
						"exportFormat": "png",
						"exportQuality": 0.8,
						"imageSpriteId": 1506738,
						"useCollisionPoly": true,
						"duration": 1
					},
					{
						"width": 41,
						"height": 8,
						"originX": 0.5121951219512195,
						"originY": 0.5,
						"originalSource": "",
						"exportFormat": "png",
						"exportQuality": 0.8,
						"imageSpriteId": 2564682,
						"useCollisionPoly": true,
						"duration": 1
					},
					{
						"width": 41,
						"height": 8,
						"originX": 0.5121951219512195,
						"originY": 0.5,
						"originalSource": "",
						"exportFormat": "png",
						"exportQuality": 0.8,
						"imageSpriteId": 7887142,
						"useCollisionPoly": true,
						"duration": 1
					},
					{
						"width": 41,
						"height": 8,
						"originX": 0.5121951219512195,
						"originY": 0.5,
						"originalSource": "",
						"exportFormat": "png",
						"exportQuality": 0.8,
						"imageSpriteId": 7856102,
						"useCollisionPoly": true,
						"duration": 1
					},
					{
						"width": 41,
						"height": 8,
						"originX": 0.5121951219512195,
						"originY": 0.5,
						"originalSource": "",
						"exportFormat": "png",
						"exportQuality": 0.8,
						"imageSpriteId": 509495,
						"useCollisionPoly": true,
						"duration": 1
					},
					{
						"width": 41,
						"height": 8,
						"originX": 0.5121951219512195,
						"originY": 0.5,
						"originalSource": "",
						"exportFormat": "png",
						"exportQuality": 0.8,
						"imageSpriteId": 9773524,
						"useCollisionPoly": true,
						"duration": 1
					},
					{
						"width": 41,
						"height": 8,
						"originX": 0.5121951219512195,
						"originY": 0.5,
						"originalSource": "",
						"exportFormat": "png",
						"exportQuality": 0.8,
						"imageSpriteId": 3082230,
						"useCollisionPoly": true,
						"duration": 1
					},
					{
						"width": 41,
						"height": 8,
						"originX": 0.5121951219512195,
						"originY": 0.5,
						"originalSource": "",
						"exportFormat": "png",
						"exportQuality": 0.8,
						"imageSpriteId": 7431399,
						"useCollisionPoly": true,
						"duration": 1
					},
					{
						"width": 41,
						"height": 8,
						"originX": 0.5121951219512195,
						"originY": 0.5,
						"originalSource": "",
						"exportFormat": "png",
						"exportQuality": 0.8,
						"imageSpriteId": 9336910,
						"useCollisionPoly": true,
						"duration": 1
					},
					{
						"width": 41,
						"height": 8,
						"originX": 0.5121951219512195,
						"originY": 0.5,
						"originalSource": "",
						"exportFormat": "png",
						"exportQuality": 0.8,
						"imageSpriteId": 6231506,
						"useCollisionPoly": true,
						"duration": 1
					},
					{
						"width": 41,
						"height": 8,
						"originX": 0.5121951219512195,
						"originY": 0.5,
						"originalSource": "",
						"exportFormat": "png",
						"exportQuality": 0.8,
						"imageSpriteId": 8902028,
						"useCollisionPoly": true,
						"duration": 1
					},
					{
						"width": 41,
						"height": 8,
						"originX": 0.5121951219512195,
						"originY": 0.5,
						"originalSource": "",
						"exportFormat": "png",
						"exportQuality": 0.8,
						"imageSpriteId": 8024927,
						"useCollisionPoly": true,
						"duration": 1
					},
					{
						"width": 41,
						"height": 8,
						"originX": 0.5121951219512195,
						"originY": 0.5,
						"originalSource": "",
						"exportFormat": "png",
						"exportQuality": 0.8,
						"imageSpriteId": 589627,
						"useCollisionPoly": true,
						"duration": 1
					},
					{
						"width": 41,
						"height": 8,
						"originX": 0.5121951219512195,
						"originY": 0.5,
						"originalSource": "",
						"exportFormat": "png",
						"exportQuality": 0.8,
						"imageSpriteId": 6386173,
						"useCollisionPoly": true,
						"duration": 1
					},
					{
						"width": 41,
						"height": 8,
						"originX": 0.5121951219512195,
						"originY": 0.5,
						"originalSource": "",
						"exportFormat": "png",
						"exportQuality": 0.8,
						"imageSpriteId": 5164175,
						"useCollisionPoly": true,
						"duration": 1
					}
				],
				"sid": 556468733913101,
				"name": "Electric",
				"isLooping": false,
				"isPingPong": false,
				"repeatCount": 1,
				"repeatTo": 0,
				"speed": 25
			},
			{
				"frames": [
					{
						"width": 41,
						"height": 8,
						"originX": 0.5121951219512195,
						"originY": 0.5,
						"originalSource": "",
						"exportFormat": "png",
						"exportQuality": 0.8,
						"imageSpriteId": 7887169,
						"useCollisionPoly": true,
						"duration": 1
					},
					{
						"width": 41,
						"height": 8,
						"originX": 0.5121951219512195,
						"originY": 0.5,
						"originalSource": "",
						"exportFormat": "png",
						"exportQuality": 0.8,
						"imageSpriteId": 1802231,
						"useCollisionPoly": true,
						"duration": 1
					},
					{
						"width": 41,
						"height": 8,
						"originX": 0.5121951219512195,
						"originY": 0.5,
						"originalSource": "",
						"exportFormat": "png",
						"exportQuality": 0.8,
						"imageSpriteId": 4734304,
						"useCollisionPoly": true,
						"duration": 1
					},
					{
						"width": 41,
						"height": 8,
						"originX": 0.5121951219512195,
						"originY": 0.5,
						"originalSource": "",
						"exportFormat": "png",
						"exportQuality": 0.8,
						"imageSpriteId": 1804812,
						"useCollisionPoly": true,
						"duration": 1
					},
					{
						"width": 41,
						"height": 8,
						"originX": 0.5121951219512195,
						"originY": 0.5,
						"originalSource": "",
						"exportFormat": "png",
						"exportQuality": 0.8,
						"imageSpriteId": 9568547,
						"useCollisionPoly": true,
						"duration": 1
					},
					{
						"width": 41,
						"height": 8,
						"originX": 0.5121951219512195,
						"originY": 0.5,
						"originalSource": "",
						"exportFormat": "png",
						"exportQuality": 0.8,
						"imageSpriteId": 9272387,
						"useCollisionPoly": true,
						"duration": 1
					},
					{
						"width": 41,
						"height": 8,
						"originX": 0.5121951219512195,
						"originY": 0.5,
						"originalSource": "",
						"exportFormat": "png",
						"exportQuality": 0.8,
						"imageSpriteId": 9920707,
						"useCollisionPoly": true,
						"duration": 1
					},
					{
						"width": 41,
						"height": 8,
						"originX": 0.5121951219512195,
						"originY": 0.5,
						"originalSource": "",
						"exportFormat": "png",
						"exportQuality": 0.8,
						"imageSpriteId": 2988520,
						"useCollisionPoly": true,
						"duration": 1
					},
					{
						"width": 41,
						"height": 8,
						"originX": 0.5121951219512195,
						"originY": 0.5,
						"originalSource": "",
						"exportFormat": "png",
						"exportQuality": 0.8,
						"imageSpriteId": 463819,
						"useCollisionPoly": true,
						"duration": 1
					},
					{
						"width": 41,
						"height": 8,
						"originX": 0.5121951219512195,
						"originY": 0.5,
						"originalSource": "",
						"exportFormat": "png",
						"exportQuality": 0.8,
						"imageSpriteId": 4524580,
						"useCollisionPoly": true,
						"duration": 1
					},
					{
						"width": 41,
						"height": 8,
						"originX": 0.5121951219512195,
						"originY": 0.5,
						"originalSource": "",
						"exportFormat": "png",
						"exportQuality": 0.8,
						"imageSpriteId": 6475139,
						"useCollisionPoly": true,
						"duration": 1
					},
					{
						"width": 41,
						"height": 8,
						"originX": 0.5121951219512195,
						"originY": 0.5,
						"originalSource": "",
						"exportFormat": "png",
						"exportQuality": 0.8,
						"imageSpriteId": 3953474,
						"useCollisionPoly": true,
						"duration": 1
					},
					{
						"width": 41,
						"height": 8,
						"originX": 0.5121951219512195,
						"originY": 0.5,
						"originalSource": "",
						"exportFormat": "png",
						"exportQuality": 0.8,
						"imageSpriteId": 1577283,
						"useCollisionPoly": true,
						"duration": 1
					},
					{
						"width": 41,
						"height": 8,
						"originX": 0.5121951219512195,
						"originY": 0.5,
						"originalSource": "",
						"exportFormat": "png",
						"exportQuality": 0.8,
						"imageSpriteId": 8215639,
						"useCollisionPoly": true,
						"duration": 1
					},
					{
						"width": 41,
						"height": 8,
						"originX": 0.5121951219512195,
						"originY": 0.5,
						"originalSource": "",
						"exportFormat": "png",
						"exportQuality": 0.8,
						"imageSpriteId": 3286106,
						"useCollisionPoly": true,
						"duration": 1
					},
					{
						"width": 41,
						"height": 8,
						"originX": 0.5121951219512195,
						"originY": 0.5,
						"originalSource": "",
						"exportFormat": "png",
						"exportQuality": 0.8,
						"imageSpriteId": 9519544,
						"useCollisionPoly": true,
						"duration": 1
					},
					{
						"width": 41,
						"height": 8,
						"originX": 0.5121951219512195,
						"originY": 0.5,
						"originalSource": "",
						"exportFormat": "png",
						"exportQuality": 0.8,
						"imageSpriteId": 1879330,
						"useCollisionPoly": true,
						"duration": 1
					},
					{
						"width": 41,
						"height": 8,
						"originX": 0.5121951219512195,
						"originY": 0.5,
						"originalSource": "",
						"exportFormat": "png",
						"exportQuality": 0.8,
						"imageSpriteId": 3639632,
						"useCollisionPoly": true,
						"duration": 1
					},
					{
						"width": 41,
						"height": 8,
						"originX": 0.5121951219512195,
						"originY": 0.5,
						"originalSource": "",
						"exportFormat": "png",
						"exportQuality": 0.8,
						"imageSpriteId": 7018551,
						"useCollisionPoly": true,
						"duration": 1
					},
					{
						"width": 41,
						"height": 8,
						"originX": 0.5121951219512195,
						"originY": 0.5,
						"originalSource": "",
						"exportFormat": "png",
						"exportQuality": 0.8,
						"imageSpriteId": 9710728,
						"useCollisionPoly": true,
						"duration": 1
					},
					{
						"width": 41,
						"height": 8,
						"originX": 0.5121951219512195,
						"originY": 0.5,
						"originalSource": "",
						"exportFormat": "png",
						"exportQuality": 0.8,
						"imageSpriteId": 1692433,
						"useCollisionPoly": true,
						"duration": 1
					},
					{
						"width": 41,
						"height": 8,
						"originX": 0.5121951219512195,
						"originY": 0.5,
						"originalSource": "",
						"exportFormat": "png",
						"exportQuality": 0.8,
						"imageSpriteId": 2359315,
						"useCollisionPoly": true,
						"duration": 1
					},
					{
						"width": 41,
						"height": 8,
						"originX": 0.5121951219512195,
						"originY": 0.5,
						"originalSource": "",
						"exportFormat": "png",
						"exportQuality": 0.8,
						"imageSpriteId": 735574,
						"useCollisionPoly": true,
						"duration": 1
					},
					{
						"width": 41,
						"height": 8,
						"originX": 0.5121951219512195,
						"originY": 0.5,
						"originalSource": "",
						"exportFormat": "png",
						"exportQuality": 0.8,
						"imageSpriteId": 7907634,
						"useCollisionPoly": true,
						"duration": 1
					},
					{
						"width": 41,
						"height": 8,
						"originX": 0.5121951219512195,
						"originY": 0.5,
						"originalSource": "",
						"exportFormat": "png",
						"exportQuality": 0.8,
						"imageSpriteId": 8345922,
						"useCollisionPoly": true,
						"duration": 1
					},
					{
						"width": 41,
						"height": 8,
						"originX": 0.5121951219512195,
						"originY": 0.5,
						"originalSource": "",
						"exportFormat": "png",
						"exportQuality": 0.8,
						"imageSpriteId": 3262628,
						"useCollisionPoly": true,
						"duration": 1
					},
					{
						"width": 41,
						"height": 8,
						"originX": 0.5121951219512195,
						"originY": 0.5,
						"originalSource": "",
						"exportFormat": "png",
						"exportQuality": 0.8,
						"imageSpriteId": 3314211,
						"useCollisionPoly": true,
						"duration": 1
					},
					{
						"width": 41,
						"height": 8,
						"originX": 0.5121951219512195,
						"originY": 0.5,
						"originalSource": "",
						"exportFormat": "png",
						"exportQuality": 0.8,
						"imageSpriteId": 9624921,
						"useCollisionPoly": true,
						"duration": 1
					},
					{
						"width": 41,
						"height": 8,
						"originX": 0.5121951219512195,
						"originY": 0.5,
						"originalSource": "",
						"exportFormat": "png",
						"exportQuality": 0.8,
						"imageSpriteId": 832930,
						"useCollisionPoly": true,
						"duration": 1
					},
					{
						"width": 41,
						"height": 8,
						"originX": 0.5121951219512195,
						"originY": 0.5,
						"originalSource": "",
						"exportFormat": "png",
						"exportQuality": 0.8,
						"imageSpriteId": 5267738,
						"useCollisionPoly": true,
						"duration": 1
					},
					{
						"width": 41,
						"height": 8,
						"originX": 0.5121951219512195,
						"originY": 0.5,
						"originalSource": "",
						"exportFormat": "png",
						"exportQuality": 0.8,
						"imageSpriteId": 1474361,
						"useCollisionPoly": true,
						"duration": 1
					},
					{
						"width": 41,
						"height": 8,
						"originX": 0.5121951219512195,
						"originY": 0.5,
						"originalSource": "",
						"exportFormat": "png",
						"exportQuality": 0.8,
						"imageSpriteId": 6907712,
						"useCollisionPoly": true,
						"duration": 1
					},
					{
						"width": 41,
						"height": 8,
						"originX": 0.5121951219512195,
						"originY": 0.5,
						"originalSource": "",
						"exportFormat": "png",
						"exportQuality": 0.8,
						"imageSpriteId": 7087061,
						"useCollisionPoly": true,
						"duration": 1
					},
					{
						"width": 41,
						"height": 8,
						"originX": 0.5121951219512195,
						"originY": 0.5,
						"originalSource": "",
						"exportFormat": "png",
						"exportQuality": 0.8,
						"imageSpriteId": 1357879,
						"useCollisionPoly": true,
						"duration": 1
					},
					{
						"width": 41,
						"height": 8,
						"originX": 0.5121951219512195,
						"originY": 0.5,
						"originalSource": "",
						"exportFormat": "png",
						"exportQuality": 0.8,
						"imageSpriteId": 9977233,
						"useCollisionPoly": true,
						"duration": 1
					},
					{
						"width": 41,
						"height": 8,
						"originX": 0.5121951219512195,
						"originY": 0.5,
						"originalSource": "",
						"exportFormat": "png",
						"exportQuality": 0.8,
						"imageSpriteId": 2813912,
						"useCollisionPoly": true,
						"duration": 1
					},
					{
						"width": 41,
						"height": 8,
						"originX": 0.5121951219512195,
						"originY": 0.5,
						"originalSource": "",
						"exportFormat": "png",
						"exportQuality": 0.8,
						"imageSpriteId": 5101819,
						"useCollisionPoly": true,
						"duration": 1
					},
					{
						"width": 41,
						"height": 8,
						"originX": 0.5121951219512195,
						"originY": 0.5,
						"originalSource": "",
						"exportFormat": "png",
						"exportQuality": 0.8,
						"imageSpriteId": 7902175,
						"useCollisionPoly": true,
						"duration": 1
					},
					{
						"width": 41,
						"height": 8,
						"originX": 0.5121951219512195,
						"originY": 0.5,
						"originalSource": "",
						"exportFormat": "png",
						"exportQuality": 0.8,
						"imageSpriteId": 4154608,
						"useCollisionPoly": true,
						"duration": 1
					},
					{
						"width": 41,
						"height": 8,
						"originX": 0.5121951219512195,
						"originY": 0.5,
						"originalSource": "",
						"exportFormat": "png",
						"exportQuality": 0.8,
						"imageSpriteId": 3618791,
						"useCollisionPoly": true,
						"duration": 1
					}
				],
				"sid": 299711023477234,
				"name": "Fire",
				"isLooping": false,
				"isPingPong": false,
				"repeatCount": 1,
				"repeatTo": 0,
				"speed": 25
			},
			{
				"frames": [
					{
						"width": 41,
						"height": 8,
						"originX": 0.5121951219512195,
						"originY": 0.5,
						"originalSource": "",
						"exportFormat": "png",
						"exportQuality": 0.8,
						"imageSpriteId": 6521527,
						"useCollisionPoly": true,
						"duration": 1
					},
					{
						"width": 41,
						"height": 8,
						"originX": 0.5121951219512195,
						"originY": 0.5,
						"originalSource": "",
						"exportFormat": "png",
						"exportQuality": 0.8,
						"imageSpriteId": 5214952,
						"useCollisionPoly": true,
						"duration": 1
					},
					{
						"width": 41,
						"height": 8,
						"originX": 0.5121951219512195,
						"originY": 0.5,
						"originalSource": "",
						"exportFormat": "png",
						"exportQuality": 0.8,
						"imageSpriteId": 68894,
						"useCollisionPoly": true,
						"duration": 1
					},
					{
						"width": 41,
						"height": 8,
						"originX": 0.5121951219512195,
						"originY": 0.5,
						"originalSource": "",
						"exportFormat": "png",
						"exportQuality": 0.8,
						"imageSpriteId": 5913000,
						"useCollisionPoly": true,
						"duration": 1
					},
					{
						"width": 41,
						"height": 8,
						"originX": 0.5121951219512195,
						"originY": 0.5,
						"originalSource": "",
						"exportFormat": "png",
						"exportQuality": 0.8,
						"imageSpriteId": 5559945,
						"useCollisionPoly": true,
						"duration": 1
					},
					{
						"width": 41,
						"height": 8,
						"originX": 0.5121951219512195,
						"originY": 0.5,
						"originalSource": "",
						"exportFormat": "png",
						"exportQuality": 0.8,
						"imageSpriteId": 2681252,
						"useCollisionPoly": true,
						"duration": 1
					},
					{
						"width": 41,
						"height": 8,
						"originX": 0.5121951219512195,
						"originY": 0.5,
						"originalSource": "",
						"exportFormat": "png",
						"exportQuality": 0.8,
						"imageSpriteId": 9321561,
						"useCollisionPoly": true,
						"duration": 1
					},
					{
						"width": 41,
						"height": 8,
						"originX": 0.5121951219512195,
						"originY": 0.5,
						"originalSource": "",
						"exportFormat": "png",
						"exportQuality": 0.8,
						"imageSpriteId": 2102182,
						"useCollisionPoly": true,
						"duration": 1
					},
					{
						"width": 41,
						"height": 8,
						"originX": 0.5121951219512195,
						"originY": 0.5,
						"originalSource": "",
						"exportFormat": "png",
						"exportQuality": 0.8,
						"imageSpriteId": 6210645,
						"useCollisionPoly": true,
						"duration": 1
					},
					{
						"width": 41,
						"height": 8,
						"originX": 0.5121951219512195,
						"originY": 0.5,
						"originalSource": "",
						"exportFormat": "png",
						"exportQuality": 0.8,
						"imageSpriteId": 910745,
						"useCollisionPoly": true,
						"duration": 1
					},
					{
						"width": 41,
						"height": 8,
						"originX": 0.5121951219512195,
						"originY": 0.5,
						"originalSource": "",
						"exportFormat": "png",
						"exportQuality": 0.8,
						"imageSpriteId": 2395057,
						"useCollisionPoly": true,
						"duration": 1
					},
					{
						"width": 41,
						"height": 8,
						"originX": 0.5121951219512195,
						"originY": 0.5,
						"originalSource": "",
						"exportFormat": "png",
						"exportQuality": 0.8,
						"imageSpriteId": 433569,
						"useCollisionPoly": true,
						"duration": 1
					},
					{
						"width": 41,
						"height": 8,
						"originX": 0.5121951219512195,
						"originY": 0.5,
						"originalSource": "",
						"exportFormat": "png",
						"exportQuality": 0.8,
						"imageSpriteId": 418290,
						"useCollisionPoly": true,
						"duration": 1
					},
					{
						"width": 41,
						"height": 8,
						"originX": 0.5121951219512195,
						"originY": 0.5,
						"originalSource": "",
						"exportFormat": "png",
						"exportQuality": 0.8,
						"imageSpriteId": 9162486,
						"useCollisionPoly": true,
						"duration": 1
					},
					{
						"width": 41,
						"height": 8,
						"originX": 0.5121951219512195,
						"originY": 0.5,
						"originalSource": "",
						"exportFormat": "png",
						"exportQuality": 0.8,
						"imageSpriteId": 8589792,
						"useCollisionPoly": true,
						"duration": 1
					},
					{
						"width": 41,
						"height": 8,
						"originX": 0.5121951219512195,
						"originY": 0.5,
						"originalSource": "",
						"exportFormat": "png",
						"exportQuality": 0.8,
						"imageSpriteId": 6902975,
						"useCollisionPoly": true,
						"duration": 1
					},
					{
						"width": 41,
						"height": 8,
						"originX": 0.5121951219512195,
						"originY": 0.5,
						"originalSource": "",
						"exportFormat": "png",
						"exportQuality": 0.8,
						"imageSpriteId": 6207555,
						"useCollisionPoly": true,
						"duration": 1
					},
					{
						"width": 41,
						"height": 8,
						"originX": 0.5121951219512195,
						"originY": 0.5,
						"originalSource": "",
						"exportFormat": "png",
						"exportQuality": 0.8,
						"imageSpriteId": 1043497,
						"useCollisionPoly": true,
						"duration": 1
					},
					{
						"width": 41,
						"height": 8,
						"originX": 0.5121951219512195,
						"originY": 0.5,
						"originalSource": "",
						"exportFormat": "png",
						"exportQuality": 0.8,
						"imageSpriteId": 7979218,
						"useCollisionPoly": true,
						"duration": 1
					},
					{
						"width": 41,
						"height": 8,
						"originX": 0.5121951219512195,
						"originY": 0.5,
						"originalSource": "",
						"exportFormat": "png",
						"exportQuality": 0.8,
						"imageSpriteId": 5166242,
						"useCollisionPoly": true,
						"duration": 1
					},
					{
						"width": 41,
						"height": 8,
						"originX": 0.5121951219512195,
						"originY": 0.5,
						"originalSource": "",
						"exportFormat": "png",
						"exportQuality": 0.8,
						"imageSpriteId": 2950043,
						"useCollisionPoly": true,
						"duration": 1
					},
					{
						"width": 41,
						"height": 8,
						"originX": 0.5121951219512195,
						"originY": 0.5,
						"originalSource": "",
						"exportFormat": "png",
						"exportQuality": 0.8,
						"imageSpriteId": 1976437,
						"useCollisionPoly": true,
						"duration": 1
					},
					{
						"width": 41,
						"height": 8,
						"originX": 0.5121951219512195,
						"originY": 0.5,
						"originalSource": "",
						"exportFormat": "png",
						"exportQuality": 0.8,
						"imageSpriteId": 1229292,
						"useCollisionPoly": true,
						"duration": 1
					},
					{
						"width": 41,
						"height": 8,
						"originX": 0.5121951219512195,
						"originY": 0.5,
						"originalSource": "",
						"exportFormat": "png",
						"exportQuality": 0.8,
						"imageSpriteId": 8142824,
						"useCollisionPoly": true,
						"duration": 1
					},
					{
						"width": 41,
						"height": 8,
						"originX": 0.5121951219512195,
						"originY": 0.5,
						"originalSource": "",
						"exportFormat": "png",
						"exportQuality": 0.8,
						"imageSpriteId": 292715,
						"useCollisionPoly": true,
						"duration": 1
					},
					{
						"width": 41,
						"height": 8,
						"originX": 0.5121951219512195,
						"originY": 0.5,
						"originalSource": "",
						"exportFormat": "png",
						"exportQuality": 0.8,
						"imageSpriteId": 1370336,
						"useCollisionPoly": true,
						"duration": 1
					},
					{
						"width": 41,
						"height": 8,
						"originX": 0.5121951219512195,
						"originY": 0.5,
						"originalSource": "",
						"exportFormat": "png",
						"exportQuality": 0.8,
						"imageSpriteId": 1121868,
						"useCollisionPoly": true,
						"duration": 1
					},
					{
						"width": 41,
						"height": 8,
						"originX": 0.5121951219512195,
						"originY": 0.5,
						"originalSource": "",
						"exportFormat": "png",
						"exportQuality": 0.8,
						"imageSpriteId": 4854669,
						"useCollisionPoly": true,
						"duration": 1
					},
					{
						"width": 41,
						"height": 8,
						"originX": 0.5121951219512195,
						"originY": 0.5,
						"originalSource": "",
						"exportFormat": "png",
						"exportQuality": 0.8,
						"imageSpriteId": 5469701,
						"useCollisionPoly": true,
						"duration": 1
					},
					{
						"width": 41,
						"height": 8,
						"originX": 0.5121951219512195,
						"originY": 0.5,
						"originalSource": "",
						"exportFormat": "png",
						"exportQuality": 0.8,
						"imageSpriteId": 6042321,
						"useCollisionPoly": true,
						"duration": 1
					},
					{
						"width": 41,
						"height": 8,
						"originX": 0.5121951219512195,
						"originY": 0.5,
						"originalSource": "",
						"exportFormat": "png",
						"exportQuality": 0.8,
						"imageSpriteId": 8581733,
						"useCollisionPoly": true,
						"duration": 1
					},
					{
						"width": 41,
						"height": 8,
						"originX": 0.5121951219512195,
						"originY": 0.5,
						"originalSource": "",
						"exportFormat": "png",
						"exportQuality": 0.8,
						"imageSpriteId": 6685360,
						"useCollisionPoly": true,
						"duration": 1
					},
					{
						"width": 41,
						"height": 8,
						"originX": 0.5121951219512195,
						"originY": 0.5,
						"originalSource": "",
						"exportFormat": "png",
						"exportQuality": 0.8,
						"imageSpriteId": 5427509,
						"useCollisionPoly": true,
						"duration": 1
					},
					{
						"width": 41,
						"height": 8,
						"originX": 0.5121951219512195,
						"originY": 0.5,
						"originalSource": "",
						"exportFormat": "png",
						"exportQuality": 0.8,
						"imageSpriteId": 2452104,
						"useCollisionPoly": true,
						"duration": 1
					},
					{
						"width": 41,
						"height": 8,
						"originX": 0.5121951219512195,
						"originY": 0.5,
						"originalSource": "",
						"exportFormat": "png",
						"exportQuality": 0.8,
						"imageSpriteId": 7912598,
						"useCollisionPoly": true,
						"duration": 1
					},
					{
						"width": 41,
						"height": 8,
						"originX": 0.5121951219512195,
						"originY": 0.5,
						"originalSource": "",
						"exportFormat": "png",
						"exportQuality": 0.8,
						"imageSpriteId": 2013735,
						"useCollisionPoly": true,
						"duration": 1
					},
					{
						"width": 41,
						"height": 8,
						"originX": 0.5121951219512195,
						"originY": 0.5,
						"originalSource": "",
						"exportFormat": "png",
						"exportQuality": 0.8,
						"imageSpriteId": 3323783,
						"useCollisionPoly": true,
						"duration": 1
					},
					{
						"width": 41,
						"height": 8,
						"originX": 0.5121951219512195,
						"originY": 0.5,
						"originalSource": "",
						"exportFormat": "png",
						"exportQuality": 0.8,
						"imageSpriteId": 3020578,
						"useCollisionPoly": true,
						"duration": 1
					},
					{
						"width": 41,
						"height": 8,
						"originX": 0.5121951219512195,
						"originY": 0.5,
						"originalSource": "",
						"exportFormat": "png",
						"exportQuality": 0.8,
						"imageSpriteId": 3198932,
						"useCollisionPoly": true,
						"duration": 1
					},
					{
						"width": 41,
						"height": 8,
						"originX": 0.5121951219512195,
						"originY": 0.5,
						"originalSource": "",
						"exportFormat": "png",
						"exportQuality": 0.8,
						"imageSpriteId": 4283961,
						"useCollisionPoly": true,
						"duration": 1
					}
				],
				"sid": 953392125314396,
				"name": "Ice",
				"isLooping": false,
				"isPingPong": false,
				"repeatCount": 1,
				"repeatTo": 0,
				"speed": 25
			}
		],
		"subfolders": []
	}
}