{
	"name": "Melee_Enemy_Minor",
	"plugin-id": "Sprite",
	"sid": 479808422501921,
	"isGlobal": false,
	"instanceVariables": [],
	"behaviorTypes": [
		{
			"behaviorId": "solid",
			"name": "Solid",
			"sid": 281092781757943
		},
		{
			"behaviorId": "Bullet",
			"name": "Bullet",
			"sid": 403895607235016
		}
	],
	"effectTypes": [],
	"animations": {
		"items": [
			{
				"frames": [
					{
						"width": 622,
						"height": 600,
						"originX": 0.5,
						"originY": 0.5,
						"originalSource": "",
						"exportFormat": "png",
						"exportQuality": 0.8,
						"imageSpriteId": 3994024,
						"useCollisionPoly": true,
						"duration": 1
					}
				],
				"sid": 252265176200206,
				"name": "Normal",
				"isLooping": false,
				"isPingPong": false,
				"repeatCount": 1,
				"repeatTo": 0,
				"speed": 5
			},
			{
				"frames": [
					{
						"width": 622,
						"height": 600,
						"originX": 0.5,
						"originY": 0.5,
						"originalSource": "",
						"exportFormat": "png",
						"exportQuality": 0.8,
						"imageSpriteId": 2441720,
						"useCollisionPoly": true,
						"duration": 1
					}
				],
				"sid": 489911772786862,
				"name": "Burning",
				"isLooping": false,
				"isPingPong": false,
				"repeatCount": 1,
				"repeatTo": 0,
				"speed": 5
			},
			{
				"frames": [
					{
						"width": 622,
						"height": 600,
						"originX": 0.5,
						"originY": 0.5,
						"originalSource": "",
						"exportFormat": "png",
						"exportQuality": 0.8,
						"imageSpriteId": 5883798,
						"useCollisionPoly": true,
						"duration": 1
					}
				],
				"sid": 839398903178132,
				"name": "Frozen",
				"isLooping": false,
				"isPingPong": false,
				"repeatCount": 1,
				"repeatTo": 0,
				"speed": 5
			},
			{
				"frames": [
					{
						"width": 622,
						"height": 600,
						"originX": 0.5,
						"originY": 0.5,
						"originalSource": "",
						"exportFormat": "png",
						"exportQuality": 0.8,
						"imageSpriteId": 7543213,
						"useCollisionPoly": true,
						"duration": 1
					}
				],
				"sid": 623944742292940,
				"name": "Paralyzed",
				"isLooping": false,
				"isPingPong": false,
				"repeatCount": 1,
				"repeatTo": 0,
				"speed": 5
			}
		],
		"subfolders": []
	}
}